claudable_helper/__init__.py
claudable_helper/cli/__init__.py
claudable_helper/cli/base.py
claudable_helper/cli/manager.py
claudable_helper/cli/unified_manager.py
claudable_helper/cli/adapters/__init__.py
claudable_helper/cli/adapters/claude_code.py
claudable_helper/cli/adapters/codex_cli.py
claudable_helper/cli/adapters/cursor_agent.py
claudable_helper/cli/adapters/gemini_cli.py
claudable_helper/cli/adapters/qwen_cli.py
claudable_helper/core/__init__.py
claudable_helper/core/config.py
claudable_helper/core/crypto.py
claudable_helper/core/terminal_ui.py
claudable_helper/core/websocket/__init__.py
claudable_helper/core/websocket/manager.py
claudable_helper/external/__init__.py
claudable_helper/external/claude_code_sdk.py
claudable_helper/models/__init__.py
claudable_helper/models/env_vars.py
claudable_helper/models/messages.py
claudable_helper/models/project_services.py
claudable_helper/models/projects.py
claudable_helper/models/sessions.py
claudable_helper/models/tokens.py
claudable_helper/services/__init__.py
claudable_helper/services/assets.py
claudable_helper/services/claude_act.py
claudable_helper/services/cli_session_manager.py
claudable_helper/services/env_manager.py
claudable_helper/services/filesystem.py
claudable_helper/services/git_ops.py
claudable_helper/services/github_service.py
claudable_helper/services/local_runtime.py
claudable_helper/services/token_service.py
claudable_helper/services/vercel_service.py
claudable_helper/services/project/initializer.py
jolt_mcp-0.5.2.dist-info/licenses/LICENCE
jolt_mcp-0.5.2.dist-info/METADATA
jolt_mcp-0.5.2.dist-info/WHEEL
jolt_mcp-0.5.2.dist-info/entry_points.txt
jolt_mcp-0.5.2.dist-info/top_level.txt
jolt_mcp-0.5.2.dist-info/RECORD
